setup.py
OE_Distributions.egg-info/PKG-INFO
OE_Distributions.egg-info/SOURCES.txt
OE_Distributions.egg-info/dependency_links.txt
OE_Distributions.egg-info/not-zip-safe
OE_Distributions.egg-info/top_level.txt
distributions/Binomialdistribution.py
distributions/Gaussiandistribution.py
distributions/Generaldistribution.py
distributions/__init__.py